{
  "last_updated": "2025-11-10T16:05:45.547Z",
  "source": "coinlore",
  "version": "1.0.0",
  "coins": [
    {
      "symbol": "BTC",
      "name": "Bitcoin",
      "price_usd": 105052.98,
      "percent_change_24h": 1.27,
      "percent_change_1h": 0.17,
      "percent_change_7d": -2.7,
      "rank": 1,
      "market_cap_usd": 2095001613440.6,
      "volume_24h": 51016318934.33869
    },
    {
      "symbol": "ETH",
      "name": "Ethereum",
      "price_usd": 3519.32,
      "percent_change_24h": 0.09,
      "percent_change_1h": -0.55,
      "percent_change_7d": -5.79,
      "rank": 2,
      "market_cap_usd": 424795579857.25,
      "volume_24h": 25032781700.44605
    },
    {
      "symbol": "USDT",
      "name": "Tether",
      "price_usd": 1,
      "percent_change_24h": -0.02,
      "percent_change_1h": 0.06,
      "percent_change_7d": 0.09,
      "rank": 3,
      "market_cap_usd": 171986159400.79,
      "volume_24h": 95824991797.3886
    },
    {
      "symbol": "XRP",
      "name": "XRP",
      "price_usd": 2.53,
      "percent_change_24h": 9.46,
      "percent_change_1h": 1.03,
      "percent_change_7d": 4.17,
      "rank": 4,
      "market_cap_usd": 151284441966.57,
      "volume_24h": 4787139487.395841
    },
    {
      "symbol": "BNB",
      "name": "Binance Coin",
      "price_usd": 979.82,
      "percent_change_24h": -1.47,
      "percent_change_1h": -0.47,
      "percent_change_7d": -6.14,
      "rank": 5,
      "market_cap_usd": 136377241979.89,
      "volume_24h": 1891613917.7980926
    },
    {
      "symbol": "SOL",
      "name": "Solana",
      "price_usd": 166.18,
      "percent_change_24h": 2.25,
      "percent_change_1h": 0.11,
      "percent_change_7d": -6.28,
      "rank": 6,
      "market_cap_usd": 90262639232.86,
      "volume_24h": 4132815133.231126
    },
    {
      "symbol": "USDC",
      "name": "USD Coin",
      "price_usd": 1,
      "percent_change_24h": 0.03,
      "percent_change_1h": 0.03,
      "percent_change_7d": 0.07,
      "rank": 7,
      "market_cap_usd": 74004555849.99,
      "volume_24h": 8283153366.9987545
    },
    {
      "symbol": "TRX",
      "name": "TRON",
      "price_usd": 0.293665,
      "percent_change_24h": 0.76,
      "percent_change_1h": 0.15,
      "percent_change_7d": -0.03,
      "rank": 9,
      "market_cap_usd": 27800108097.56,
      "volume_24h": 842255337.0575676
    },
    {
      "symbol": "DOGE",
      "name": "Dogecoin",
      "price_usd": 0.179193,
      "percent_change_24h": 0.65,
      "percent_change_1h": -0.12,
      "percent_change_7d": 2.53,
      "rank": 10,
      "market_cap_usd": 27160747497.67,
      "volume_24h": 1820622708.6134727
    },
    {
      "symbol": "ADA",
      "name": "Cardano",
      "price_usd": 0.584856,
      "percent_change_24h": 1.67,
      "percent_change_1h": 0.09,
      "percent_change_7d": 1.73,
      "rank": 11,
      "market_cap_usd": 20938124346.53,
      "volume_24h": 646031366.003228
    },
    {
      "symbol": "HYPE",
      "name": "Hyperliquid",
      "price_usd": 41.19,
      "percent_change_24h": 0.66,
      "percent_change_1h": -0.82,
      "percent_change_7d": 1.48,
      "rank": 13,
      "market_cap_usd": 13754449008.7,
      "volume_24h": 217171377.41238979
    },
    {
      "symbol": "LINK",
      "name": "ChainLink",
      "price_usd": 16.08,
      "percent_change_24h": 1.66,
      "percent_change_1h": -0.2,
      "percent_change_7d": -1.56,
      "rank": 18,
      "market_cap_usd": 10903211146.86,
      "volume_24h": 677451549.9546093
    },
    {
      "symbol": "BCH",
      "name": "Bitcoin Cash",
      "price_usd": 512.9,
      "percent_change_24h": 2.65,
      "percent_change_1h": -0.54,
      "percent_change_7d": -2.73,
      "rank": 19,
      "market_cap_usd": 10230529216.7,
      "volume_24h": 311513551.3416332
    },
    {
      "symbol": "ZEC",
      "name": "Zcash",
      "price_usd": 613.09,
      "percent_change_24h": -4.92,
      "percent_change_1h": 1.41,
      "percent_change_7d": 56.85,
      "rank": 20,
      "market_cap_usd": 9948290003.99,
      "volume_24h": 2233775879.340096
    },
    {
      "symbol": "LTC",
      "name": "Litecoin",
      "price_usd": 107.42,
      "percent_change_24h": 0.73,
      "percent_change_1h": 0.84,
      "percent_change_7d": 14.22,
      "rank": 23,
      "market_cap_usd": 8199093698.9,
      "volume_24h": 1534777086.224528
    },
    {
      "symbol": "AVAX",
      "name": "Avalanche",
      "price_usd": 17.94,
      "percent_change_24h": 1.45,
      "percent_change_1h": 0.15,
      "percent_change_7d": 2.45,
      "rank": 26,
      "market_cap_usd": 7574564684.99,
      "volume_24h": 369292035.27467185
    },
    {
      "symbol": "XMR",
      "name": "Monero",
      "price_usd": 396.9,
      "percent_change_24h": -8.19,
      "percent_change_1h": 0.85,
      "percent_change_7d": 17.78,
      "rank": 27,
      "market_cap_usd": 7321503188.2,
      "volume_24h": 239518716.12087283
    },
    {
      "symbol": "SHIB",
      "name": "Shiba Inu",
      "price_usd": 0.00001,
      "percent_change_24h": 0.6,
      "percent_change_1h": 0.27,
      "percent_change_7d": 2.91,
      "rank": 29,
      "market_cap_usd": 5901204768.77,
      "volume_24h": 27078511.5288198
    },
    {
      "symbol": "PEPE",
      "name": "Pepe",
      "price_usd": 0.000006,
      "percent_change_24h": 0.54,
      "percent_change_1h": 0.47,
      "percent_change_7d": -1.46,
      "rank": 42,
      "market_cap_usd": 2576902112.43,
      "volume_24h": 8430426.039807804
    },
    {
      "symbol": "ETC",
      "name": "Ethereum Classic",
      "price_usd": 16.19,
      "percent_change_24h": 0.35,
      "percent_change_1h": 0.23,
      "percent_change_7d": 4.24,
      "rank": 43,
      "market_cap_usd": 2487311131.14,
      "volume_24h": 438873409.7485619
    },
    {
      "symbol": "PI",
      "name": "Pi",
      "price_usd": 0.230081,
      "percent_change_24h": 1.78,
      "percent_change_1h": 0.02,
      "percent_change_7d": -5,
      "rank": 49,
      "market_cap_usd": 1885864576.6,
      "volume_24h": 26743050.469901048
    },
    {
      "symbol": "XAUT",
      "name": "Tether Gold",
      "price_usd": 4075.28,
      "percent_change_24h": 2.11,
      "percent_change_1h": 0,
      "percent_change_7d": 1.79,
      "rank": 56,
      "market_cap_usd": 1530562468.56,
      "volume_24h": 83948539.64424428
    },
    {
      "symbol": "KAS",
      "name": "Kaspa",
      "price_usd": 0.052305,
      "percent_change_24h": 0.37,
      "percent_change_1h": -0.46,
      "percent_change_7d": 7.74,
      "rank": 60,
      "market_cap_usd": 1397816126.91,
      "volume_24h": 45510173.570208065
    },
    {
      "symbol": "DASH",
      "name": "Dash",
      "price_usd": 79.61,
      "percent_change_24h": -7.74,
      "percent_change_1h": 0.37,
      "percent_change_7d": -4.39,
      "rank": 76,
      "market_cap_usd": 992548680.51,
      "volume_24h": 908017429.5940396
    },
    {
      "symbol": "RVN",
      "name": "Ravencoin",
      "price_usd": 0.010589,
      "percent_change_24h": -2.39,
      "percent_change_1h": 0.25,
      "percent_change_7d": 12.7,
      "rank": 224,
      "market_cap_usd": 165302190.71,
      "volume_24h": 14319665.990175454
    },
    {
      "symbol": "BELLS",
      "name": "Bellscoin",
      "price_usd": 0.130319,
      "percent_change_24h": -2.38,
      "percent_change_1h": 0.25,
      "percent_change_7d": 7.75,
      "rank": 997,
      "market_cap_usd": 7955812.85,
      "volume_24h": 45900.583848109345
    },
    {
      "symbol": "VTC",
      "name": "Vertcoin",
      "price_usd": 0.068392,
      "percent_change_24h": -2.4,
      "percent_change_1h": -0.26,
      "percent_change_7d": 3.92,
      "rank": 1132,
      "market_cap_usd": 5007800.3,
      "volume_24h": 13751.680853347823
    }
  ]
}