{
  "last_updated": "2025-11-03T09:38:11.693Z",
  "source": "coinlore",
  "version": "1.0.0",
  "coins": [
    {
      "symbol": "BTC",
      "name": "Bitcoin",
      "price_usd": 107352.31,
      "percent_change_24h": -3.13,
      "percent_change_1h": 0.08,
      "percent_change_7d": -5.28,
      "rank": 1,
      "market_cap_usd": 2140855577371.7,
      "volume_24h": 41575075242.00796
    },
    {
      "symbol": "ETH",
      "name": "Ethereum",
      "price_usd": 3712.72,
      "percent_change_24h": -4.61,
      "percent_change_1h": 0.28,
      "percent_change_7d": -8.8,
      "rank": 2,
      "market_cap_usd": 448139585826.54,
      "volume_24h": 25158266640.090775
    },
    {
      "symbol": "USDT",
      "name": "Tether",
      "price_usd": 1,
      "percent_change_24h": -0.03,
      "percent_change_1h": 0.03,
      "percent_change_7d": -0.02,
      "rank": 3,
      "market_cap_usd": 171974394755.59,
      "volume_24h": 84472097250.59839
    },
    {
      "symbol": "XRP",
      "name": "XRP",
      "price_usd": 2.41,
      "percent_change_24h": -4.61,
      "percent_change_1h": 0.09,
      "percent_change_7d": -7.83,
      "rank": 4,
      "market_cap_usd": 144128745130.33,
      "volume_24h": 2992867498.3093596
    },
    {
      "symbol": "BNB",
      "name": "Binance Coin",
      "price_usd": 1024.36,
      "percent_change_24h": -6.05,
      "percent_change_1h": -0.07,
      "percent_change_7d": -9.11,
      "rank": 5,
      "market_cap_usd": 142576760157.73,
      "volume_24h": 1776360864.2559142
    },
    {
      "symbol": "SOL",
      "name": "Solana",
      "price_usd": 175.6,
      "percent_change_24h": -6.07,
      "percent_change_1h": -0.09,
      "percent_change_7d": -11.07,
      "rank": 6,
      "market_cap_usd": 95375765781.89,
      "volume_24h": 4225509602.3895855
    },
    {
      "symbol": "USDC",
      "name": "USD Coin",
      "price_usd": 0.999991,
      "percent_change_24h": -0.01,
      "percent_change_1h": 0.01,
      "percent_change_7d": 0.02,
      "rank": 7,
      "market_cap_usd": 73978624937.71,
      "volume_24h": 8330979165.489305
    },
    {
      "symbol": "TRX",
      "name": "TRON",
      "price_usd": 0.295203,
      "percent_change_24h": -0.38,
      "percent_change_1h": 0.5,
      "percent_change_7d": -1.2,
      "rank": 9,
      "market_cap_usd": 27945712656.16,
      "volume_24h": 1021577020.2991942
    },
    {
      "symbol": "DOGE",
      "name": "Dogecoin",
      "price_usd": 0.173684,
      "percent_change_24h": -7.22,
      "percent_change_1h": 0.31,
      "percent_change_7d": -13.77,
      "rank": 10,
      "market_cap_usd": 26325658760.11,
      "volume_24h": 1668857635.7387426
    },
    {
      "symbol": "ADA",
      "name": "Cardano",
      "price_usd": 0.577647,
      "percent_change_24h": -5.79,
      "percent_change_1h": 0.25,
      "percent_change_7d": -14.01,
      "rank": 11,
      "market_cap_usd": 20680030064.9,
      "volume_24h": 725801577.0379376
    },
    {
      "symbol": "HYPE",
      "name": "Hyperliquid",
      "price_usd": 40.87,
      "percent_change_24h": -5.13,
      "percent_change_1h": 0.13,
      "percent_change_7d": -12.85,
      "rank": 14,
      "market_cap_usd": 13646962018.99,
      "volume_24h": 308014633.2943663
    },
    {
      "symbol": "LINK",
      "name": "ChainLink",
      "price_usd": 16.08,
      "percent_change_24h": -8.15,
      "percent_change_1h": -0.18,
      "percent_change_7d": -11.39,
      "rank": 17,
      "market_cap_usd": 10905178608.87,
      "volume_24h": 666348888.6682606
    },
    {
      "symbol": "BCH",
      "name": "Bitcoin Cash",
      "price_usd": 523.24,
      "percent_change_24h": -5.28,
      "percent_change_1h": -0.65,
      "percent_change_7d": -5.26,
      "rank": 18,
      "market_cap_usd": 10436697646.44,
      "volume_24h": 419304422.0346916
    },
    {
      "symbol": "AVAX",
      "name": "Avalanche",
      "price_usd": 17.44,
      "percent_change_24h": -7.51,
      "percent_change_1h": 0.27,
      "percent_change_7d": -13.62,
      "rank": 22,
      "market_cap_usd": 7366090631,
      "volume_24h": 318533841.2258395
    },
    {
      "symbol": "LTC",
      "name": "Litecoin",
      "price_usd": 92.94,
      "percent_change_24h": -7.49,
      "percent_change_1h": -0.17,
      "percent_change_7d": -6.39,
      "rank": 23,
      "market_cap_usd": 7093253424.87,
      "volume_24h": 1000619768.362992
    },
    {
      "symbol": "XMR",
      "name": "Monero",
      "price_usd": 348.78,
      "percent_change_24h": -2.11,
      "percent_change_1h": 2.84,
      "percent_change_7d": 1,
      "rank": 24,
      "market_cap_usd": 6433863389.95,
      "volume_24h": 173829756.1065154
    },
    {
      "symbol": "ZEC",
      "name": "Zcash",
      "price_usd": 382.8,
      "percent_change_24h": -8.14,
      "percent_change_1h": -1.8,
      "percent_change_7d": 11.23,
      "rank": 25,
      "market_cap_usd": 6211434047.11,
      "volume_24h": 937999957.9907975
    },
    {
      "symbol": "SHIB",
      "name": "Shiba Inu",
      "price_usd": 0.00001,
      "percent_change_24h": -5.35,
      "percent_change_1h": 0.34,
      "percent_change_7d": -7.39,
      "rank": 27,
      "market_cap_usd": 5688151640.82,
      "volume_24h": 26631632.231545035
    },
    {
      "symbol": "PEPE",
      "name": "Pepe",
      "price_usd": 0.000006,
      "percent_change_24h": -7.87,
      "percent_change_1h": 0.25,
      "percent_change_7d": -14.74,
      "rank": 38,
      "market_cap_usd": 2596612886.8,
      "volume_24h": 9639471.198087655
    },
    {
      "symbol": "ETC",
      "name": "Ethereum Classic",
      "price_usd": 15.35,
      "percent_change_24h": -7.21,
      "percent_change_1h": 0.29,
      "percent_change_7d": -6.28,
      "rank": 42,
      "market_cap_usd": 2358431622.31,
      "volume_24h": 359943408.80382735
    },
    {
      "symbol": "PI",
      "name": "Pi",
      "price_usd": 0.240891,
      "percent_change_24h": -3.77,
      "percent_change_1h": 0.46,
      "percent_change_7d": 12.75,
      "rank": 47,
      "market_cap_usd": 1974471344.42,
      "volume_24h": 30727635.49505807
    },
    {
      "symbol": "XAUT",
      "name": "Tether Gold",
      "price_usd": 4000.08,
      "percent_change_24h": 0.05,
      "percent_change_1h": -0.25,
      "percent_change_7d": -2.49,
      "rank": 52,
      "market_cap_usd": 1502319454.16,
      "volume_24h": 82514253.42302528
    },
    {
      "symbol": "KAS",
      "name": "Kaspa",
      "price_usd": 0.049356,
      "percent_change_24h": -7.54,
      "percent_change_1h": 0.76,
      "percent_change_7d": -13.66,
      "rank": 57,
      "market_cap_usd": 1319012711.37,
      "volume_24h": 33348509.414669044
    },
    {
      "symbol": "DASH",
      "name": "Dash",
      "price_usd": 80.92,
      "percent_change_24h": -7.66,
      "percent_change_1h": -4.69,
      "percent_change_7d": 61.81,
      "rank": 72,
      "market_cap_usd": 1008835178.97,
      "volume_24h": 2021416412.4487386
    },
    {
      "symbol": "RVN",
      "name": "Ravencoin",
      "price_usd": 0.009337,
      "percent_change_24h": -6.23,
      "percent_change_1h": 0.06,
      "percent_change_7d": -7.74,
      "rank": 235,
      "market_cap_usd": 145756368.3,
      "volume_24h": 10934920.046759004
    },
    {
      "symbol": "VTC",
      "name": "Vertcoin",
      "price_usd": 0.065142,
      "percent_change_24h": -4.92,
      "percent_change_1h": -0.59,
      "percent_change_7d": -5.81,
      "rank": 1167,
      "market_cap_usd": 4769814.85,
      "volume_24h": 15426.255203002895
    }
  ]
}