{
  "last_updated": "2025-12-11T11:23:05.295Z",
  "source": "coinlore",
  "version": "1.0.0",
  "coins": [
    {
      "symbol": "BTC",
      "name": "Bitcoin",
      "price_usd": 90368.95,
      "percent_change_24h": -2.13,
      "percent_change_1h": 0.11,
      "percent_change_7d": -3.61,
      "rank": 1,
      "market_cap_usd": 1802819511697,
      "volume_24h": 42778883830.52676
    },
    {
      "symbol": "ETH",
      "name": "Ethereum",
      "price_usd": 3198.96,
      "percent_change_24h": -3.56,
      "percent_change_1h": 0.1,
      "percent_change_7d": 0.37,
      "rank": 2,
      "market_cap_usd": 386126706755.36,
      "volume_24h": 24412854216.794346
    },
    {
      "symbol": "USDT",
      "name": "Tether",
      "price_usd": 1,
      "percent_change_24h": 0,
      "percent_change_1h": 0.01,
      "percent_change_7d": 0.05,
      "rank": 3,
      "market_cap_usd": 171980330260.28,
      "volume_24h": 80759767521.41031
    },
    {
      "symbol": "BNB",
      "name": "Binance Coin",
      "price_usd": 867.15,
      "percent_change_24h": -2.38,
      "percent_change_1h": 0.05,
      "percent_change_7d": -5.67,
      "rank": 4,
      "market_cap_usd": 120694880735.24,
      "volume_24h": 1304186358.4557807
    },
    {
      "symbol": "XRP",
      "name": "XRP",
      "price_usd": 2.01,
      "percent_change_24h": -2.71,
      "percent_change_1h": 0.09,
      "percent_change_7d": -8.61,
      "rank": 5,
      "market_cap_usd": 120441075823.42,
      "volume_24h": 3105980350.7492332
    },
    {
      "symbol": "USDC",
      "name": "USD Coin",
      "price_usd": 0.999715,
      "percent_change_24h": 0,
      "percent_change_1h": 0,
      "percent_change_7d": 0,
      "rank": 6,
      "market_cap_usd": 73958261584.53,
      "volume_24h": 7790301569.782494
    },
    {
      "symbol": "SOL",
      "name": "Solana",
      "price_usd": 130.92,
      "percent_change_24h": -4.64,
      "percent_change_1h": 0.17,
      "percent_change_7d": -9.73,
      "rank": 7,
      "market_cap_usd": 71107805857.15,
      "volume_24h": 4923340570.447918
    },
    {
      "symbol": "TRX",
      "name": "TRON",
      "price_usd": 0.28063,
      "percent_change_24h": 0.55,
      "percent_change_1h": 0.01,
      "percent_change_7d": 0.03,
      "rank": 9,
      "market_cap_usd": 26566146247.62,
      "volume_24h": 619322217.0041087
    },
    {
      "symbol": "DOGE",
      "name": "Dogecoin",
      "price_usd": 0.137898,
      "percent_change_24h": -5.57,
      "percent_change_1h": 0.09,
      "percent_change_7d": -9.62,
      "rank": 10,
      "market_cap_usd": 20932222783.96,
      "volume_24h": 1459802127.5348027
    },
    {
      "symbol": "ADA",
      "name": "Cardano",
      "price_usd": 0.423869,
      "percent_change_24h": -8.54,
      "percent_change_1h": 0.02,
      "percent_change_7d": -6.31,
      "rank": 11,
      "market_cap_usd": 15174697306,
      "volume_24h": 792563761.3916378
    },
    {
      "symbol": "BCH",
      "name": "Bitcoin Cash",
      "price_usd": 561.12,
      "percent_change_24h": -1.36,
      "percent_change_1h": 0.39,
      "percent_change_7d": -5.48,
      "rank": 15,
      "market_cap_usd": 11196379482.58,
      "volume_24h": 347172806.7794914
    },
    {
      "symbol": "LINK",
      "name": "ChainLink",
      "price_usd": 13.59,
      "percent_change_24h": -4.07,
      "percent_change_1h": 0.34,
      "percent_change_7d": -7.51,
      "rank": 17,
      "market_cap_usd": 9212941670.53,
      "volume_24h": 674451586.4598284
    },
    {
      "symbol": "HYPE",
      "name": "Hyperliquid",
      "price_usd": 27.22,
      "percent_change_24h": -6.94,
      "percent_change_1h": -2.37,
      "percent_change_7d": -21.92,
      "rank": 18,
      "market_cap_usd": 9089838117.27,
      "volume_24h": 221861364.69968033
    },
    {
      "symbol": "XMR",
      "name": "Monero",
      "price_usd": 404.87,
      "percent_change_24h": 1.99,
      "percent_change_1h": 0.69,
      "percent_change_7d": -0.87,
      "rank": 20,
      "market_cap_usd": 7468608012.81,
      "volume_24h": 216123072.1502965
    },
    {
      "symbol": "ZEC",
      "name": "Zcash",
      "price_usd": 429.83,
      "percent_change_24h": -0.51,
      "percent_change_1h": 2.81,
      "percent_change_7d": 26.17,
      "rank": 21,
      "market_cap_usd": 6974564758.52,
      "volume_24h": 1055906537.3670744
    },
    {
      "symbol": "LTC",
      "name": "Litecoin",
      "price_usd": 80.99,
      "percent_change_24h": -3.61,
      "percent_change_1h": 0.05,
      "percent_change_7d": -6.05,
      "rank": 22,
      "market_cap_usd": 6181728234.24,
      "volume_24h": 597742843.4238659
    },
    {
      "symbol": "AVAX",
      "name": "Avalanche",
      "price_usd": 13.28,
      "percent_change_24h": -7.38,
      "percent_change_1h": -0.33,
      "percent_change_7d": -10.7,
      "rank": 23,
      "market_cap_usd": 5607434654.23,
      "volume_24h": 380291566.52965873
    },
    {
      "symbol": "SHIB",
      "name": "Shiba Inu",
      "price_usd": 0.000008,
      "percent_change_24h": -3.12,
      "percent_change_1h": 0.2,
      "percent_change_7d": -8.78,
      "rank": 27,
      "market_cap_usd": 4860391603.64,
      "volume_24h": 23617164.7599284
    },
    {
      "symbol": "ETC",
      "name": "Ethereum Classic",
      "price_usd": 13.05,
      "percent_change_24h": -4.07,
      "percent_change_1h": 0.2,
      "percent_change_7d": -8.43,
      "rank": 40,
      "market_cap_usd": 2004401037.2,
      "volume_24h": 164712230.6134116
    },
    {
      "symbol": "PEPE",
      "name": "Pepe",
      "price_usd": 0.000004,
      "percent_change_24h": -5.46,
      "percent_change_1h": 0.33,
      "percent_change_7d": -8.24,
      "rank": 42,
      "market_cap_usd": 1871312536.78,
      "volume_24h": 4986269.339754149
    },
    {
      "symbol": "PI",
      "name": "Pi",
      "price_usd": 0.210287,
      "percent_change_24h": -2.13,
      "percent_change_1h": 0.08,
      "percent_change_7d": -10.68,
      "rank": 45,
      "market_cap_usd": 1723620611.13,
      "volume_24h": 14579626.462297805
    },
    {
      "symbol": "XAUT",
      "name": "Tether Gold",
      "price_usd": 4214.79,
      "percent_change_24h": 0.48,
      "percent_change_1h": -0.1,
      "percent_change_7d": 0.26,
      "rank": 49,
      "market_cap_usd": 1582957655.81,
      "volume_24h": 133251971.96957967
    },
    {
      "symbol": "KAS",
      "name": "Kaspa",
      "price_usd": 0.047813,
      "percent_change_24h": -4.54,
      "percent_change_1h": 0.42,
      "percent_change_7d": -16.23,
      "rank": 53,
      "market_cap_usd": 1277789514.36,
      "volume_24h": 20685219.082434814
    },
    {
      "symbol": "DASH",
      "name": "Dash",
      "price_usd": 47,
      "percent_change_24h": -3.6,
      "percent_change_1h": 1.04,
      "percent_change_7d": -4.56,
      "rank": 88,
      "market_cap_usd": 586674378.2,
      "volume_24h": 133292546.40978187
    },
    {
      "symbol": "RVN",
      "name": "Ravencoin",
      "price_usd": 0.007815,
      "percent_change_24h": -2.97,
      "percent_change_1h": 0.38,
      "percent_change_7d": -5.8,
      "rank": 223,
      "market_cap_usd": 121997048.14,
      "volume_24h": 7101822.938236348
    },
    {
      "symbol": "VTC",
      "name": "Vertcoin",
      "price_usd": 0.072457,
      "percent_change_24h": -2.17,
      "percent_change_1h": 0.01,
      "percent_change_7d": 3.33,
      "rank": 1038,
      "market_cap_usd": 5313897.69,
      "volume_24h": 15324.026241404523
    },
    {
      "symbol": "BELLS",
      "name": "Bellscoin",
      "price_usd": 0.078257,
      "percent_change_24h": 3.36,
      "percent_change_1h": 1.09,
      "percent_change_7d": -6.07,
      "rank": 1085,
      "market_cap_usd": 4777484.84,
      "volume_24h": 40051.21555532235
    }
  ]
}