{
  "last_updated": "2025-11-09T04:05:59.463Z",
  "source": "coinlore",
  "version": "1.0.0",
  "coins": [
    {
      "symbol": "BTC",
      "name": "Bitcoin",
      "price_usd": 101636.35,
      "percent_change_24h": -0.98,
      "percent_change_1h": -0.01,
      "percent_change_7d": -7.84,
      "rank": 1,
      "market_cap_usd": 2026866053581.2,
      "volume_24h": 32569208267.49837
    },
    {
      "symbol": "ETH",
      "name": "Ethereum",
      "price_usd": 3375.26,
      "percent_change_24h": -2.34,
      "percent_change_1h": 0.16,
      "percent_change_7d": -13.31,
      "rank": 2,
      "market_cap_usd": 407407183138.21,
      "volume_24h": 16832765327.070679
    },
    {
      "symbol": "USDT",
      "name": "Tether",
      "price_usd": 1,
      "percent_change_24h": 0.12,
      "percent_change_1h": 0.07,
      "percent_change_7d": -0.04,
      "rank": 3,
      "market_cap_usd": 172021624464.17,
      "volume_24h": 70027564979.59583
    },
    {
      "symbol": "BNB",
      "name": "Binance Coin",
      "price_usd": 980.86,
      "percent_change_24h": -1.63,
      "percent_change_1h": -0.24,
      "percent_change_7d": -10.19,
      "rank": 4,
      "market_cap_usd": 136522409902.35,
      "volume_24h": 1680714183.7583227
    },
    {
      "symbol": "XRP",
      "name": "XRP",
      "price_usd": 2.25,
      "percent_change_24h": -2.98,
      "percent_change_1h": -0.28,
      "percent_change_7d": -9.85,
      "rank": 5,
      "market_cap_usd": 134696440348.4,
      "volume_24h": 2256357761.4858174
    },
    {
      "symbol": "SOL",
      "name": "Solana",
      "price_usd": 155.84,
      "percent_change_24h": -4.2,
      "percent_change_1h": -0.14,
      "percent_change_7d": -16.34,
      "rank": 6,
      "market_cap_usd": 84643424025.18,
      "volume_24h": 2488429523.1982923
    },
    {
      "symbol": "USDC",
      "name": "USD Coin",
      "price_usd": 1,
      "percent_change_24h": -0.02,
      "percent_change_1h": 0,
      "percent_change_7d": -0.01,
      "rank": 7,
      "market_cap_usd": 73989753504.2,
      "volume_24h": 5778017223.303908
    },
    {
      "symbol": "TRX",
      "name": "TRON",
      "price_usd": 0.289622,
      "percent_change_24h": -0.81,
      "percent_change_1h": 0.01,
      "percent_change_7d": -2.45,
      "rank": 9,
      "market_cap_usd": 27417391854.92,
      "volume_24h": 754600514.8718055
    },
    {
      "symbol": "DOGE",
      "name": "Dogecoin",
      "price_usd": 0.171977,
      "percent_change_24h": -4.45,
      "percent_change_1h": -0.13,
      "percent_change_7d": -8.15,
      "rank": 10,
      "market_cap_usd": 26066922549.27,
      "volume_24h": 1616935263.097314
    },
    {
      "symbol": "ADA",
      "name": "Cardano",
      "price_usd": 0.550097,
      "percent_change_24h": -5.6,
      "percent_change_1h": -0.51,
      "percent_change_7d": -10.11,
      "rank": 11,
      "market_cap_usd": 19693738036,
      "volume_24h": 521228008.86887765
    },
    {
      "symbol": "HYPE",
      "name": "Hyperliquid",
      "price_usd": 40.07,
      "percent_change_24h": -5.17,
      "percent_change_1h": 1.13,
      "percent_change_7d": -7.38,
      "rank": 13,
      "market_cap_usd": 13380504259.65,
      "volume_24h": 205421641.552673
    },
    {
      "symbol": "LINK",
      "name": "ChainLink",
      "price_usd": 15.09,
      "percent_change_24h": -4.39,
      "percent_change_1h": -0.42,
      "percent_change_7d": -12.44,
      "rank": 17,
      "market_cap_usd": 10233583840.38,
      "volume_24h": 547004558.3157426
    },
    {
      "symbol": "BCH",
      "name": "Bitcoin Cash",
      "price_usd": 491.85,
      "percent_change_24h": -2.8,
      "percent_change_1h": -0.87,
      "percent_change_7d": -11.04,
      "rank": 18,
      "market_cap_usd": 9810571842.85,
      "volume_24h": 271338447.9730662
    },
    {
      "symbol": "ZEC",
      "name": "Zcash",
      "price_usd": 540.08,
      "percent_change_24h": -9.22,
      "percent_change_1h": -0.83,
      "percent_change_7d": 29.51,
      "rank": 20,
      "market_cap_usd": 8763535449.98,
      "volume_24h": 3394968517.1587124
    },
    {
      "symbol": "LTC",
      "name": "Litecoin",
      "price_usd": 100,
      "percent_change_24h": -1,
      "percent_change_1h": -1.51,
      "percent_change_7d": 1.37,
      "rank": 22,
      "market_cap_usd": 7632318053.81,
      "volume_24h": 1399484598.8928711
    },
    {
      "symbol": "XMR",
      "name": "Monero",
      "price_usd": 409.33,
      "percent_change_24h": 13.04,
      "percent_change_1h": 5.65,
      "percent_change_7d": 19.55,
      "rank": 23,
      "market_cap_usd": 7550833754.53,
      "volume_24h": 201349173.65858078
    },
    {
      "symbol": "AVAX",
      "name": "Avalanche",
      "price_usd": 16.89,
      "percent_change_24h": -5.36,
      "percent_change_1h": -0.2,
      "percent_change_7d": -9.35,
      "rank": 26,
      "market_cap_usd": 7130305571.88,
      "volume_24h": 336910434.9323846
    },
    {
      "symbol": "SHIB",
      "name": "Shiba Inu",
      "price_usd": 0.00001,
      "percent_change_24h": -4.29,
      "percent_change_1h": -0.63,
      "percent_change_7d": -4.71,
      "rank": 28,
      "market_cap_usd": 5695612202.01,
      "volume_24h": 28329147.858890798
    },
    {
      "symbol": "PEPE",
      "name": "Pepe",
      "price_usd": 0.000006,
      "percent_change_24h": -5.16,
      "percent_change_1h": -0.43,
      "percent_change_7d": -12.28,
      "rank": 41,
      "market_cap_usd": 2467072140.08,
      "volume_24h": 9274643.31265498
    },
    {
      "symbol": "ETC",
      "name": "Ethereum Classic",
      "price_usd": 15.9,
      "percent_change_24h": -7.45,
      "percent_change_1h": -0.35,
      "percent_change_7d": -2.7,
      "rank": 42,
      "market_cap_usd": 2442194916.47,
      "volume_24h": 449391129.86505926
    },
    {
      "symbol": "PI",
      "name": "Pi",
      "price_usd": 0.220185,
      "percent_change_24h": -2,
      "percent_change_1h": -0.67,
      "percent_change_7d": -11.28,
      "rank": 48,
      "market_cap_usd": 1804755113.86,
      "volume_24h": 19291484.703296736
    },
    {
      "symbol": "XAUT",
      "name": "Tether Gold",
      "price_usd": 3985.24,
      "percent_change_24h": -0.12,
      "percent_change_1h": 0.03,
      "percent_change_7d": -0.44,
      "rank": 54,
      "market_cap_usd": 1496744322.55,
      "volume_24h": 22682733.494209286
    },
    {
      "symbol": "KAS",
      "name": "Kaspa",
      "price_usd": 0.049431,
      "percent_change_24h": -3.44,
      "percent_change_1h": -0.68,
      "percent_change_7d": -8.04,
      "rank": 60,
      "market_cap_usd": 1321026324.95,
      "volume_24h": 46835795.07843515
    },
    {
      "symbol": "DASH",
      "name": "Dash",
      "price_usd": 74.48,
      "percent_change_24h": -18,
      "percent_change_1h": -3,
      "percent_change_7d": 5.27,
      "rank": 74,
      "market_cap_usd": 928581950.32,
      "volume_24h": 1586243942.6115181
    },
    {
      "symbol": "RVN",
      "name": "Ravencoin",
      "price_usd": 0.010717,
      "percent_change_24h": -2.17,
      "percent_change_1h": -0.58,
      "percent_change_7d": 7.72,
      "rank": 210,
      "market_cap_usd": 167299344.16,
      "volume_24h": 66908462.272552416
    },
    {
      "symbol": "BELLS",
      "name": "Bellscoin",
      "price_usd": 0.134664,
      "percent_change_24h": 3.69,
      "percent_change_1h": 0.59,
      "percent_change_7d": 17.36,
      "rank": 975,
      "market_cap_usd": 8221097.85,
      "volume_24h": 90628.10542517588
    },
    {
      "symbol": "VTC",
      "name": "Vertcoin",
      "price_usd": 0.065662,
      "percent_change_24h": -8.92,
      "percent_change_1h": 0.03,
      "percent_change_7d": -2.23,
      "rank": 1137,
      "market_cap_usd": 4807891.18,
      "volume_24h": 15757.235330278418
    }
  ]
}