{
  "last_updated": "2025-12-15T22:49:35.600Z",
  "source": "coinlore",
  "version": "1.0.0",
  "coins": [
    {
      "symbol": "BTC",
      "name": "Bitcoin",
      "price_usd": 86044.61,
      "percent_change_24h": -2.42,
      "percent_change_1h": -0.06,
      "percent_change_7d": -6.68,
      "rank": 1,
      "market_cap_usd": 1717603022249.1,
      "volume_24h": 38458070517.9792
    },
    {
      "symbol": "ETH",
      "name": "Ethereum",
      "price_usd": 2941.18,
      "percent_change_24h": -3.94,
      "percent_change_1h": 0.04,
      "percent_change_7d": -6.91,
      "rank": 2,
      "market_cap_usd": 355011727404,
      "volume_24h": 20991214134.426117
    },
    {
      "symbol": "USDT",
      "name": "Tether",
      "price_usd": 1,
      "percent_change_24h": -0.1,
      "percent_change_1h": -0.01,
      "percent_change_7d": 0.05,
      "rank": 3,
      "market_cap_usd": 172051683965.89,
      "volume_24h": 68966534510.47751
    },
    {
      "symbol": "BNB",
      "name": "Binance Coin",
      "price_usd": 852.41,
      "percent_change_24h": -2.87,
      "percent_change_1h": 0.14,
      "percent_change_7d": -6.31,
      "rank": 4,
      "market_cap_usd": 118643383306.36,
      "volume_24h": 1144019972.66266
    },
    {
      "symbol": "XRP",
      "name": "XRP",
      "price_usd": 1.88,
      "percent_change_24h": -5.06,
      "percent_change_1h": -0.5,
      "percent_change_7d": -10.28,
      "rank": 5,
      "market_cap_usd": 112665406038.15,
      "volume_24h": 2708998679.7364154
    },
    {
      "symbol": "USDC",
      "name": "USD Coin",
      "price_usd": 0.999947,
      "percent_change_24h": 0.01,
      "percent_change_1h": 0,
      "percent_change_7d": 0.02,
      "rank": 6,
      "market_cap_usd": 73975384341.55,
      "volume_24h": 6131838675.115593
    },
    {
      "symbol": "SOL",
      "name": "Solana",
      "price_usd": 126,
      "percent_change_24h": -2.97,
      "percent_change_1h": 0.19,
      "percent_change_7d": -9.49,
      "rank": 7,
      "market_cap_usd": 68436622911.89,
      "volume_24h": 4015557898.015669
    },
    {
      "symbol": "TRX",
      "name": "TRON",
      "price_usd": 0.278441,
      "percent_change_24h": 0.64,
      "percent_change_1h": 0.03,
      "percent_change_7d": -2.83,
      "rank": 8,
      "market_cap_usd": 26358941631.04,
      "volume_24h": 696654549.5829055
    },
    {
      "symbol": "DOGE",
      "name": "Dogecoin",
      "price_usd": 0.128514,
      "percent_change_24h": -4.07,
      "percent_change_1h": -0.06,
      "percent_change_7d": -10.72,
      "rank": 10,
      "market_cap_usd": 21575299662.46,
      "volume_24h": 1193665634.4617162
    },
    {
      "symbol": "ADA",
      "name": "Cardano",
      "price_usd": 0.383056,
      "percent_change_24h": -3.14,
      "percent_change_1h": -0.14,
      "percent_change_7d": -11.88,
      "rank": 12,
      "market_cap_usd": 13713562600.75,
      "volume_24h": 513198213.8910444
    },
    {
      "symbol": "BCH",
      "name": "Bitcoin Cash",
      "price_usd": 529.72,
      "percent_change_24h": -4.96,
      "percent_change_1h": -0.29,
      "percent_change_7d": -11.4,
      "rank": 14,
      "market_cap_usd": 10576608511.84,
      "volume_24h": 291252272.7685849
    },
    {
      "symbol": "HYPE",
      "name": "Hyperliquid",
      "price_usd": 27.59,
      "percent_change_24h": -3.29,
      "percent_change_1h": 0.02,
      "percent_change_7d": -9.7,
      "rank": 17,
      "market_cap_usd": 9211425541.71,
      "volume_24h": 203829445.70747977
    },
    {
      "symbol": "LINK",
      "name": "ChainLink",
      "price_usd": 12.71,
      "percent_change_24h": -4.15,
      "percent_change_1h": -0.22,
      "percent_change_7d": -9.86,
      "rank": 18,
      "market_cap_usd": 8616050734.5,
      "volume_24h": 531259731.2211977
    },
    {
      "symbol": "XMR",
      "name": "Monero",
      "price_usd": 403.7,
      "percent_change_24h": -1.45,
      "percent_change_1h": -0.01,
      "percent_change_7d": 6.08,
      "rank": 19,
      "market_cap_usd": 7446984490.67,
      "volume_24h": 191237189.45030826
    },
    {
      "symbol": "ZEC",
      "name": "Zcash",
      "price_usd": 410.48,
      "percent_change_24h": 2.89,
      "percent_change_1h": 1.82,
      "percent_change_7d": 3.4,
      "rank": 21,
      "market_cap_usd": 6660623485.08,
      "volume_24h": 940037022.9401138
    },
    {
      "symbol": "LTC",
      "name": "Litecoin",
      "price_usd": 77.07,
      "percent_change_24h": -1.77,
      "percent_change_1h": 0.18,
      "percent_change_7d": -8.12,
      "rank": 23,
      "market_cap_usd": 5882406176.28,
      "volume_24h": 491363130.31746495
    },
    {
      "symbol": "AVAX",
      "name": "Avalanche",
      "price_usd": 12.32,
      "percent_change_24h": -4.27,
      "percent_change_1h": -0.16,
      "percent_change_7d": -10.75,
      "rank": 25,
      "market_cap_usd": 5203803624.36,
      "volume_24h": 307081362.3251327
    },
    {
      "symbol": "SHIB",
      "name": "Shiba Inu",
      "price_usd": 0.000008,
      "percent_change_24h": -2.85,
      "percent_change_1h": -0.33,
      "percent_change_7d": -7.61,
      "rank": 28,
      "market_cap_usd": 4617746355.35,
      "volume_24h": 18651585.753800344
    },
    {
      "symbol": "ETC",
      "name": "Ethereum Classic",
      "price_usd": 12.27,
      "percent_change_24h": -3.61,
      "percent_change_1h": 0.09,
      "percent_change_7d": -9.27,
      "rank": 40,
      "market_cap_usd": 1885074188.48,
      "volume_24h": 144456264.5397114
    },
    {
      "symbol": "PEPE",
      "name": "Pepe",
      "price_usd": 0.000004,
      "percent_change_24h": -3.66,
      "percent_change_1h": 0.29,
      "percent_change_7d": -14.87,
      "rank": 41,
      "market_cap_usd": 1693775032.53,
      "volume_24h": 5763250.259020817
    },
    {
      "symbol": "PI",
      "name": "Pi",
      "price_usd": 0.198652,
      "percent_change_24h": -2.4,
      "percent_change_1h": -0.24,
      "percent_change_7d": -10.22,
      "rank": 43,
      "market_cap_usd": 1628258079.83,
      "volume_24h": 13102439.712464795
    },
    {
      "symbol": "XAUT",
      "name": "Tether Gold",
      "price_usd": 4306.43,
      "percent_change_24h": 0.06,
      "percent_change_1h": 0.05,
      "percent_change_7d": 2.41,
      "rank": 45,
      "market_cap_usd": 1617374762.69,
      "volume_24h": 156978656.32758355
    },
    {
      "symbol": "KAS",
      "name": "Kaspa",
      "price_usd": 0.042726,
      "percent_change_24h": -4.05,
      "percent_change_1h": -0.21,
      "percent_change_7d": -20.18,
      "rank": 57,
      "market_cap_usd": 1141829877.58,
      "volume_24h": 20025378.490612503
    },
    {
      "symbol": "DASH",
      "name": "Dash",
      "price_usd": 40.46,
      "percent_change_24h": -1.47,
      "percent_change_1h": 0.52,
      "percent_change_7d": -16.34,
      "rank": 90,
      "market_cap_usd": 506363329.52,
      "volume_24h": 111312363.37065499
    },
    {
      "symbol": "RVN",
      "name": "Ravencoin",
      "price_usd": 0.007302,
      "percent_change_24h": -2.21,
      "percent_change_1h": 0.41,
      "percent_change_7d": -9.89,
      "rank": 231,
      "market_cap_usd": 113996244.79,
      "volume_24h": 6346830.823958625
    },
    {
      "symbol": "VTC",
      "name": "Vertcoin",
      "price_usd": 0.068988,
      "percent_change_24h": -4.31,
      "percent_change_1h": -4.27,
      "percent_change_7d": -3.99,
      "rank": 1044,
      "market_cap_usd": 5071922.22,
      "volume_24h": 13847.265379113513
    },
    {
      "symbol": "BELLS",
      "name": "Bellscoin",
      "price_usd": 0.080074,
      "percent_change_24h": 2.63,
      "percent_change_1h": 0.1,
      "percent_change_7d": -2.64,
      "rank": 1059,
      "market_cap_usd": 4888435.77,
      "volume_24h": 31440.141835006478
    }
  ]
}