{
  "last_updated": "2025-11-14T18:24:30.831Z",
  "source": "coinlore",
  "version": "1.0.0",
  "coins": [
    {
      "symbol": "BTC",
      "name": "Bitcoin",
      "price_usd": 96026.77,
      "percent_change_24h": -3.25,
      "percent_change_1h": -0.94,
      "percent_change_7d": -6.18,
      "rank": 1,
      "market_cap_usd": 1914997934091.5,
      "volume_24h": 101415434763.55046
    },
    {
      "symbol": "ETH",
      "name": "Ethereum",
      "price_usd": 3194,
      "percent_change_24h": -1.43,
      "percent_change_1h": -0.93,
      "percent_change_7d": -5.09,
      "rank": 2,
      "market_cap_usd": 385527760475.33,
      "volume_24h": 38736660963.11263
    },
    {
      "symbol": "USDT",
      "name": "Tether",
      "price_usd": 1,
      "percent_change_24h": 0.22,
      "percent_change_1h": 0.17,
      "percent_change_7d": 0.17,
      "rank": 3,
      "market_cap_usd": 172266161537.05,
      "volume_24h": 146399062588.02948
    },
    {
      "symbol": "XRP",
      "name": "XRP",
      "price_usd": 2.32,
      "percent_change_24h": -1.87,
      "percent_change_1h": -0.37,
      "percent_change_7d": 3.87,
      "rank": 4,
      "market_cap_usd": 138787685135.94,
      "volume_24h": 6478086710.712569
    },
    {
      "symbol": "BNB",
      "name": "Binance Coin",
      "price_usd": 925.45,
      "percent_change_24h": -0.28,
      "percent_change_1h": -0.37,
      "percent_change_7d": -4.54,
      "rank": 5,
      "market_cap_usd": 128810353505.17,
      "volume_24h": 2683526142.15628
    },
    {
      "symbol": "SOL",
      "name": "Solana",
      "price_usd": 142.19,
      "percent_change_24h": -3.07,
      "percent_change_1h": -0.58,
      "percent_change_7d": -9.96,
      "rank": 6,
      "market_cap_usd": 77232828682.24,
      "volume_24h": 7482939410.383146
    },
    {
      "symbol": "USDC",
      "name": "USD Coin",
      "price_usd": 1,
      "percent_change_24h": 0.07,
      "percent_change_1h": 0.01,
      "percent_change_7d": 0.01,
      "rank": 7,
      "market_cap_usd": 74018306631.8,
      "volume_24h": 13557597168.66092
    },
    {
      "symbol": "TRX",
      "name": "TRON",
      "price_usd": 0.296006,
      "percent_change_24h": 0.81,
      "percent_change_1h": -0.58,
      "percent_change_7d": 3.16,
      "rank": 8,
      "market_cap_usd": 28021707488.28,
      "volume_24h": 1443940161.843321
    },
    {
      "symbol": "DOGE",
      "name": "Dogecoin",
      "price_usd": 0.162638,
      "percent_change_24h": -1.17,
      "percent_change_1h": -0.56,
      "percent_change_7d": -2.01,
      "rank": 10,
      "market_cap_usd": 24651501218.48,
      "volume_24h": 2944091319.4888487
    },
    {
      "symbol": "ADA",
      "name": "Cardano",
      "price_usd": 0.514165,
      "percent_change_24h": -2.52,
      "percent_change_1h": -0.54,
      "percent_change_7d": -5.61,
      "rank": 11,
      "market_cap_usd": 18407329667.22,
      "volume_24h": 971255471.5639795
    },
    {
      "symbol": "HYPE",
      "name": "Hyperliquid",
      "price_usd": 37.24,
      "percent_change_24h": 0.51,
      "percent_change_1h": -0.63,
      "percent_change_7d": -5.9,
      "rank": 13,
      "market_cap_usd": 12436379172.15,
      "volume_24h": 315846594.8834889
    },
    {
      "symbol": "BCH",
      "name": "Bitcoin Cash",
      "price_usd": 495.62,
      "percent_change_24h": -2.91,
      "percent_change_1h": -0.4,
      "percent_change_7d": 1.85,
      "rank": 17,
      "market_cap_usd": 9885836683.31,
      "volume_24h": 455456011.6746987
    },
    {
      "symbol": "LINK",
      "name": "ChainLink",
      "price_usd": 14.25,
      "percent_change_24h": -2.18,
      "percent_change_1h": -0.95,
      "percent_change_7d": -5.67,
      "rank": 18,
      "market_cap_usd": 9662747513.06,
      "volume_24h": 1058132171.829719
    },
    {
      "symbol": "ZEC",
      "name": "Zcash",
      "price_usd": 594.87,
      "percent_change_24h": 24.73,
      "percent_change_1h": 3.95,
      "percent_change_7d": 0.4,
      "rank": 19,
      "market_cap_usd": 9652570760.44,
      "volume_24h": 2349084718.4313326
    },
    {
      "symbol": "LTC",
      "name": "Litecoin",
      "price_usd": 97.99,
      "percent_change_24h": 2.76,
      "percent_change_1h": 0.99,
      "percent_change_7d": 8.81,
      "rank": 21,
      "market_cap_usd": 7478700620.12,
      "volume_24h": 1457454024.013061
    },
    {
      "symbol": "XMR",
      "name": "Monero",
      "price_usd": 394.57,
      "percent_change_24h": 5.32,
      "percent_change_1h": -0.71,
      "percent_change_7d": 8.58,
      "rank": 22,
      "market_cap_usd": 7278488915.55,
      "volume_24h": 219091829.89095077
    },
    {
      "symbol": "AVAX",
      "name": "Avalanche",
      "price_usd": 15.49,
      "percent_change_24h": -4.87,
      "percent_change_1h": -0.81,
      "percent_change_7d": -7.43,
      "rank": 24,
      "market_cap_usd": 6542252927.65,
      "volume_24h": 553106509.942614
    },
    {
      "symbol": "SHIB",
      "name": "Shiba Inu",
      "price_usd": 0.000009,
      "percent_change_24h": -0.59,
      "percent_change_1h": -0.4,
      "percent_change_7d": -0.65,
      "rank": 27,
      "market_cap_usd": 5447185624.69,
      "volume_24h": 22579154.103399318
    },
    {
      "symbol": "ETC",
      "name": "Ethereum Classic",
      "price_usd": 14.96,
      "percent_change_24h": 0.38,
      "percent_change_1h": -0.25,
      "percent_change_7d": -1.63,
      "rank": 40,
      "market_cap_usd": 2297395771.29,
      "volume_24h": 426727046.45370954
    },
    {
      "symbol": "PEPE",
      "name": "Pepe",
      "price_usd": 0.000005,
      "percent_change_24h": -6.94,
      "percent_change_1h": -1.04,
      "percent_change_7d": -10.02,
      "rank": 42,
      "market_cap_usd": 2158436379.27,
      "volume_24h": 7646537.846855947
    },
    {
      "symbol": "PI",
      "name": "Pi",
      "price_usd": 0.216995,
      "percent_change_24h": -1.21,
      "percent_change_1h": -0.31,
      "percent_change_7d": -2.22,
      "rank": 47,
      "market_cap_usd": 1778610028.33,
      "volume_24h": 26578902.29235893
    },
    {
      "symbol": "XAUT",
      "name": "Tether Gold",
      "price_usd": 4064.13,
      "percent_change_24h": -2.68,
      "percent_change_1h": -0.25,
      "percent_change_7d": 1.95,
      "rank": 49,
      "market_cap_usd": 1526372599.11,
      "volume_24h": 16477474127.514961
    },
    {
      "symbol": "KAS",
      "name": "Kaspa",
      "price_usd": 0.046302,
      "percent_change_24h": -2.79,
      "percent_change_1h": -0.96,
      "percent_change_7d": -10.18,
      "rank": 58,
      "market_cap_usd": 1237407446.63,
      "volume_24h": 43811944.11709895
    },
    {
      "symbol": "DASH",
      "name": "Dash",
      "price_usd": 74.37,
      "percent_change_24h": 18.46,
      "percent_change_1h": 2.29,
      "percent_change_7d": -35.81,
      "rank": 72,
      "market_cap_usd": 927176174.14,
      "volume_24h": 836541664.5369662
    },
    {
      "symbol": "RVN",
      "name": "Ravencoin",
      "price_usd": 0.009411,
      "percent_change_24h": -1.39,
      "percent_change_1h": -0.54,
      "percent_change_7d": -9.73,
      "rank": 222,
      "market_cap_usd": 146907558.53,
      "volume_24h": 11886356.069868352
    },
    {
      "symbol": "BELLS",
      "name": "Bellscoin",
      "price_usd": 0.111162,
      "percent_change_24h": 0.69,
      "percent_change_1h": 0.67,
      "percent_change_7d": -0.53,
      "rank": 1017,
      "market_cap_usd": 6786310.5,
      "volume_24h": 28628.951559164732
    },
    {
      "symbol": "VTC",
      "name": "Vertcoin",
      "price_usd": 0.063358,
      "percent_change_24h": -2.17,
      "percent_change_1h": -0.47,
      "percent_change_7d": -9.01,
      "rank": 1134,
      "market_cap_usd": 4639173.13,
      "volume_24h": 18074.597356135117
    }
  ]
}