{
  "last_updated": "2025-11-04T20:36:54.829Z",
  "source": "coinlore",
  "version": "1.0.0",
  "coins": [
    {
      "symbol": "BTC",
      "name": "Bitcoin",
      "price_usd": 100406.56,
      "percent_change_24h": -6.07,
      "percent_change_1h": -0.73,
      "percent_change_7d": -12.2,
      "rank": 1,
      "market_cap_usd": 2002341116056,
      "volume_24h": 64153427085.038536
    },
    {
      "symbol": "ETH",
      "name": "Ethereum",
      "price_usd": 3202.41,
      "percent_change_24h": -11.33,
      "percent_change_1h": -3.27,
      "percent_change_7d": -22.42,
      "rank": 2,
      "market_cap_usd": 386542716346.46,
      "volume_24h": 39011570175.59189
    },
    {
      "symbol": "USDT",
      "name": "Tether",
      "price_usd": 1,
      "percent_change_24h": 0.03,
      "percent_change_1h": 0,
      "percent_change_7d": 0,
      "rank": 3,
      "market_cap_usd": 172017643460.32,
      "volume_24h": 131133669026.69832
    },
    {
      "symbol": "XRP",
      "name": "XRP",
      "price_usd": 2.15,
      "percent_change_24h": -8.05,
      "percent_change_1h": -2.21,
      "percent_change_7d": -18.8,
      "rank": 4,
      "market_cap_usd": 128437669509.67,
      "volume_24h": 5573188384.712581
    },
    {
      "symbol": "BNB",
      "name": "Binance Coin",
      "price_usd": 916.93,
      "percent_change_24h": -7.87,
      "percent_change_1h": -1.59,
      "percent_change_7d": -19.29,
      "rank": 5,
      "market_cap_usd": 127624488141.64,
      "volume_24h": 2900724749.3813376
    },
    {
      "symbol": "SOL",
      "name": "Solana",
      "price_usd": 152.34,
      "percent_change_24h": -8.34,
      "percent_change_1h": -2.23,
      "percent_change_7d": -24.76,
      "rank": 6,
      "market_cap_usd": 82742391075.92,
      "volume_24h": 6601201768.342691
    },
    {
      "symbol": "USDC",
      "name": "USD Coin",
      "price_usd": 1,
      "percent_change_24h": 0.02,
      "percent_change_1h": 0,
      "percent_change_7d": 0.04,
      "rank": 7,
      "market_cap_usd": 73995152946.33,
      "volume_24h": 13647627724.761011
    },
    {
      "symbol": "TRX",
      "name": "TRON",
      "price_usd": 0.278881,
      "percent_change_24h": -1.81,
      "percent_change_1h": -0.72,
      "percent_change_7d": -6.35,
      "rank": 9,
      "market_cap_usd": 26400633506.48,
      "volume_24h": 1446278324.1717196
    },
    {
      "symbol": "DOGE",
      "name": "Dogecoin",
      "price_usd": 0.156744,
      "percent_change_24h": -6.3,
      "percent_change_1h": -1.62,
      "percent_change_7d": -21.84,
      "rank": 10,
      "market_cap_usd": 23758019619.72,
      "volume_24h": 3241036811.64191
    },
    {
      "symbol": "ADA",
      "name": "Cardano",
      "price_usd": 0.508431,
      "percent_change_24h": -7.84,
      "percent_change_1h": -2.57,
      "percent_change_7d": -23.66,
      "rank": 11,
      "market_cap_usd": 18202057981.68,
      "volume_24h": 1067934150.562522
    },
    {
      "symbol": "HYPE",
      "name": "Hyperliquid",
      "price_usd": 36.56,
      "percent_change_24h": -8.08,
      "percent_change_1h": -4.21,
      "percent_change_7d": -22.89,
      "rank": 16,
      "market_cap_usd": 12208831056.98,
      "volume_24h": 411763008.58879644
    },
    {
      "symbol": "LINK",
      "name": "ChainLink",
      "price_usd": 14.33,
      "percent_change_24h": -6.16,
      "percent_change_1h": -1.77,
      "percent_change_7d": -22.34,
      "rank": 18,
      "market_cap_usd": 9716121776.97,
      "volume_24h": 1032875655.9441454
    },
    {
      "symbol": "BCH",
      "name": "Bitcoin Cash",
      "price_usd": 482.81,
      "percent_change_24h": -6.15,
      "percent_change_1h": -1.47,
      "percent_change_7d": -13.71,
      "rank": 19,
      "market_cap_usd": 9630387449.29,
      "volume_24h": 402024656.25753397
    },
    {
      "symbol": "ZEC",
      "name": "Zcash",
      "price_usd": 401.73,
      "percent_change_24h": -1.25,
      "percent_change_1h": -0.15,
      "percent_change_7d": 21.6,
      "rank": 23,
      "market_cap_usd": 6518569806.58,
      "volume_24h": 1912930225.8132038
    },
    {
      "symbol": "AVAX",
      "name": "Avalanche",
      "price_usd": 15.39,
      "percent_change_24h": -7.37,
      "percent_change_1h": -2.51,
      "percent_change_7d": -24.61,
      "rank": 24,
      "market_cap_usd": 6500762350.73,
      "volume_24h": 474190421.0293141
    },
    {
      "symbol": "LTC",
      "name": "Litecoin",
      "price_usd": 82.22,
      "percent_change_24h": -5.9,
      "percent_change_1h": -3.2,
      "percent_change_7d": -19.45,
      "rank": 25,
      "market_cap_usd": 6275239376.42,
      "volume_24h": 1095551074.4013896
    },
    {
      "symbol": "XMR",
      "name": "Monero",
      "price_usd": 338.64,
      "percent_change_24h": -2.6,
      "percent_change_1h": -2.73,
      "percent_change_7d": -1.05,
      "rank": 26,
      "market_cap_usd": 6246819363.6,
      "volume_24h": 201505762.94784364
    },
    {
      "symbol": "SHIB",
      "name": "Shiba Inu",
      "price_usd": 0.000009,
      "percent_change_24h": -6.18,
      "percent_change_1h": -2.28,
      "percent_change_7d": -16.51,
      "rank": 29,
      "market_cap_usd": 5096913801.65,
      "volume_24h": 23124445.353234276
    },
    {
      "symbol": "PEPE",
      "name": "Pepe",
      "price_usd": 0.000005,
      "percent_change_24h": -6.51,
      "percent_change_1h": -2.29,
      "percent_change_7d": -24.86,
      "rank": 40,
      "market_cap_usd": 2266910652.25,
      "volume_24h": 8721867.49798711
    },
    {
      "symbol": "ETC",
      "name": "Ethereum Classic",
      "price_usd": 14.07,
      "percent_change_24h": -7.65,
      "percent_change_1h": -1.9,
      "percent_change_7d": -14.88,
      "rank": 43,
      "market_cap_usd": 2160685873.63,
      "volume_24h": 365767755.3384461
    },
    {
      "symbol": "PI",
      "name": "Pi",
      "price_usd": 0.223226,
      "percent_change_24h": -3.54,
      "percent_change_1h": -1.44,
      "percent_change_7d": -2.92,
      "rank": 46,
      "market_cap_usd": 1829681786.09,
      "volume_24h": 36154809.89813152
    },
    {
      "symbol": "XAUT",
      "name": "Tether Gold",
      "price_usd": 3929.91,
      "percent_change_24h": -1.97,
      "percent_change_1h": -0.07,
      "percent_change_7d": 0.33,
      "rank": 52,
      "market_cap_usd": 1475964534.09,
      "volume_24h": 108190220.1889322
    },
    {
      "symbol": "DASH",
      "name": "Dash",
      "price_usd": 112.97,
      "percent_change_24h": -0.56,
      "percent_change_1h": -5.98,
      "percent_change_7d": 133.01,
      "rank": 54,
      "market_cap_usd": 1408462427.62,
      "volume_24h": 3160574892.5517774
    },
    {
      "symbol": "KAS",
      "name": "Kaspa",
      "price_usd": 0.04256,
      "percent_change_24h": -9.73,
      "percent_change_1h": -3.23,
      "percent_change_7d": -25.81,
      "rank": 64,
      "market_cap_usd": 1137405443.63,
      "volume_24h": 41001215.631761685
    },
    {
      "symbol": "RVN",
      "name": "Ravencoin",
      "price_usd": 0.008884,
      "percent_change_24h": -1.94,
      "percent_change_1h": -1.79,
      "percent_change_7d": -11.69,
      "rank": 237,
      "market_cap_usd": 138690580,
      "volume_24h": 16008005.987164624
    },
    {
      "symbol": "VTC",
      "name": "Vertcoin",
      "price_usd": 0.065273,
      "percent_change_24h": -2.16,
      "percent_change_1h": -1.54,
      "percent_change_7d": -4.26,
      "rank": 1156,
      "market_cap_usd": 4779409.08,
      "volume_24h": 14400.709710113691
    }
  ]
}