{
  "last_updated": "2025-11-02T14:04:01.484Z",
  "source": "coinlore",
  "version": "1.0.0",
  "coins": [
    {
      "symbol": "BTC",
      "name": "Bitcoin",
      "price_usd": 110536.47,
      "percent_change_24h": 0.53,
      "percent_change_1h": -0.18,
      "percent_change_7d": -0.97,
      "rank": 1,
      "market_cap_usd": 2204355260252.2,
      "volume_24h": 32973181207.32695
    },
    {
      "symbol": "ETH",
      "name": "Ethereum",
      "price_usd": 3867.97,
      "percent_change_24h": -0.06,
      "percent_change_1h": -0.22,
      "percent_change_7d": -1.64,
      "rank": 2,
      "market_cap_usd": 466878953901.65,
      "volume_24h": 14741380175.202908
    },
    {
      "symbol": "USDT",
      "name": "Tether",
      "price_usd": 1,
      "percent_change_24h": -0.02,
      "percent_change_1h": 0.01,
      "percent_change_7d": -0.01,
      "rank": 3,
      "market_cap_usd": 172006713798.12,
      "volume_24h": 60889476139.16011
    },
    {
      "symbol": "XRP",
      "name": "XRP",
      "price_usd": 2.53,
      "percent_change_24h": 1.54,
      "percent_change_1h": -0.38,
      "percent_change_7d": -3.34,
      "rank": 4,
      "market_cap_usd": 151122042594.34,
      "volume_24h": 1803456584.85
    },
    {
      "symbol": "BNB",
      "name": "Binance Coin",
      "price_usd": 1083.08,
      "percent_change_24h": -0.23,
      "percent_change_1h": -0.22,
      "percent_change_7d": -3.24,
      "rank": 5,
      "market_cap_usd": 150750077193.33,
      "volume_24h": 1065446517.8633012
    },
    {
      "symbol": "SOL",
      "name": "Solana",
      "price_usd": 185.09,
      "percent_change_24h": -0.13,
      "percent_change_1h": -0.21,
      "percent_change_7d": -4,
      "rank": 6,
      "market_cap_usd": 100534909981.52,
      "volume_24h": 2250204989.649156
    },
    {
      "symbol": "USDC",
      "name": "USD Coin",
      "price_usd": 1,
      "percent_change_24h": 0,
      "percent_change_1h": 0.01,
      "percent_change_7d": 0.05,
      "rank": 7,
      "market_cap_usd": 73997794528.63,
      "volume_24h": 5774195545.306176
    },
    {
      "symbol": "DOGE",
      "name": "Dogecoin",
      "price_usd": 0.185132,
      "percent_change_24h": -0.8,
      "percent_change_1h": -0.68,
      "percent_change_7d": -5.26,
      "rank": 9,
      "market_cap_usd": 28060901106.47,
      "volume_24h": 743631864.9007523
    },
    {
      "symbol": "TRX",
      "name": "TRON",
      "price_usd": 0.295607,
      "percent_change_24h": -0.25,
      "percent_change_1h": 0.01,
      "percent_change_7d": -0.5,
      "rank": 10,
      "market_cap_usd": 27983940259.52,
      "volume_24h": 718247762.5632585
    },
    {
      "symbol": "ADA",
      "name": "Cardano",
      "price_usd": 0.607041,
      "percent_change_24h": -0.67,
      "percent_change_1h": -0.68,
      "percent_change_7d": -6.78,
      "rank": 11,
      "market_cap_usd": 21732335131.37,
      "volume_24h": 381611635.80718565
    },
    {
      "symbol": "HYPE",
      "name": "Hyperliquid",
      "price_usd": 42.31,
      "percent_change_24h": -3.08,
      "percent_change_1h": 0.31,
      "percent_change_7d": -4.17,
      "rank": 12,
      "market_cap_usd": 14128575938.57,
      "volume_24h": 215321686.9525817
    },
    {
      "symbol": "LINK",
      "name": "ChainLink",
      "price_usd": 17.36,
      "percent_change_24h": 0.47,
      "percent_change_1h": -0.62,
      "percent_change_7d": -2.61,
      "rank": 17,
      "market_cap_usd": 11775066370.23,
      "volume_24h": 412531822.9645205
    },
    {
      "symbol": "BCH",
      "name": "Bitcoin Cash",
      "price_usd": 532.96,
      "percent_change_24h": -3.87,
      "percent_change_1h": -0.45,
      "percent_change_7d": 4,
      "rank": 18,
      "market_cap_usd": 10630556617.62,
      "volume_24h": 376243908.51873624
    },
    {
      "symbol": "AVAX",
      "name": "Avalanche",
      "price_usd": 18.54,
      "percent_change_24h": -0.33,
      "percent_change_1h": -1.1,
      "percent_change_7d": -5.08,
      "rank": 22,
      "market_cap_usd": 7826887964.99,
      "volume_24h": 194611371.61949393
    },
    {
      "symbol": "LTC",
      "name": "Litecoin",
      "price_usd": 99.26,
      "percent_change_24h": 0.05,
      "percent_change_1h": -1.12,
      "percent_change_7d": 2.69,
      "rank": 23,
      "market_cap_usd": 7576294034.69,
      "volume_24h": 1018456282.5253448
    },
    {
      "symbol": "XMR",
      "name": "Monero",
      "price_usd": 355.52,
      "percent_change_24h": 3.64,
      "percent_change_1h": 0.58,
      "percent_change_7d": 5.99,
      "rank": 24,
      "market_cap_usd": 6558263079.26,
      "volume_24h": 144577013.78001407
    },
    {
      "symbol": "ZEC",
      "name": "Zcash",
      "price_usd": 397.67,
      "percent_change_24h": -3.65,
      "percent_change_1h": -2.38,
      "percent_change_7d": 43.42,
      "rank": 25,
      "market_cap_usd": 6452688907.84,
      "volume_24h": 864408204.067459
    },
    {
      "symbol": "SHIB",
      "name": "Shiba Inu",
      "price_usd": 0.00001,
      "percent_change_24h": 0.25,
      "percent_change_1h": -0.48,
      "percent_change_7d": 0.38,
      "rank": 27,
      "market_cap_usd": 5988411207.15,
      "volume_24h": 26800812.420728754
    },
    {
      "symbol": "PEPE",
      "name": "Pepe",
      "price_usd": 0.000007,
      "percent_change_24h": -0.13,
      "percent_change_1h": -0.72,
      "percent_change_7d": -5.72,
      "rank": 38,
      "market_cap_usd": 2801702992.46,
      "volume_24h": 9907609.349848969
    },
    {
      "symbol": "ETC",
      "name": "Ethereum Classic",
      "price_usd": 16.27,
      "percent_change_24h": -0.04,
      "percent_change_1h": -0.63,
      "percent_change_7d": 2.21,
      "rank": 41,
      "market_cap_usd": 2498681934.13,
      "volume_24h": 350874403.74183285
    },
    {
      "symbol": "PI",
      "name": "Pi",
      "price_usd": 0.248132,
      "percent_change_24h": 0.76,
      "percent_change_1h": -0.12,
      "percent_change_7d": 19.39,
      "rank": 46,
      "market_cap_usd": 2033826138.37,
      "volume_24h": 20257288.878378075
    },
    {
      "symbol": "XAUT",
      "name": "Tether Gold",
      "price_usd": 4001.86,
      "percent_change_24h": -0.06,
      "percent_change_1h": 0.03,
      "percent_change_7d": -2.63,
      "rank": 53,
      "market_cap_usd": 1502987100.45,
      "volume_24h": 37310018.30036564
    },
    {
      "symbol": "KAS",
      "name": "Kaspa",
      "price_usd": 0.052859,
      "percent_change_24h": -1.08,
      "percent_change_1h": -0.57,
      "percent_change_7d": -7.75,
      "rank": 56,
      "market_cap_usd": 1412620864.38,
      "volume_24h": 20358917.625420377
    },
    {
      "symbol": "DASH",
      "name": "Dash",
      "price_usd": 93.77,
      "percent_change_24h": 31.62,
      "percent_change_1h": 3.32,
      "percent_change_7d": 126.71,
      "rank": 67,
      "market_cap_usd": 1169106690.52,
      "volume_24h": 2852705705.568499
    },
    {
      "symbol": "RVN",
      "name": "Ravencoin",
      "price_usd": 0.009786,
      "percent_change_24h": -1.51,
      "percent_change_1h": -0.47,
      "percent_change_7d": -0.31,
      "rank": 235,
      "market_cap_usd": 152764150.78,
      "volume_24h": 8512406.990608994
    },
    {
      "symbol": "VTC",
      "name": "Vertcoin",
      "price_usd": 0.068746,
      "percent_change_24h": 2.1,
      "percent_change_1h": 0.26,
      "percent_change_7d": 2.01,
      "rank": 1156,
      "market_cap_usd": 5033686.43,
      "volume_24h": 15024.120602347411
    }
  ]
}