{
  "last_updated": "2025-12-22T10:39:22.558Z",
  "source": "coinlore",
  "version": "1.0.0",
  "coins": [
    {
      "symbol": "BTC",
      "name": "Bitcoin",
      "price_usd": 89728.72,
      "percent_change_24h": 1.27,
      "percent_change_1h": 0.07,
      "percent_change_7d": 1.73,
      "rank": 1,
      "market_cap_usd": 1791144390411.1,
      "volume_24h": 25331584514.39033
    },
    {
      "symbol": "ETH",
      "name": "Ethereum",
      "price_usd": 3039.48,
      "percent_change_24h": 1.41,
      "percent_change_1h": -0.01,
      "percent_change_7d": -0.82,
      "rank": 2,
      "market_cap_usd": 366877405540.23,
      "volume_24h": 11784418929.830267
    },
    {
      "symbol": "USDT",
      "name": "Tether",
      "price_usd": 1,
      "percent_change_24h": 0,
      "percent_change_1h": -0.01,
      "percent_change_7d": -0.14,
      "rank": 3,
      "market_cap_usd": 171951540371.67,
      "volume_24h": 46575684328.33999
    },
    {
      "symbol": "BNB",
      "name": "Binance Coin",
      "price_usd": 865.36,
      "percent_change_24h": 1.15,
      "percent_change_1h": -0.17,
      "percent_change_7d": -1.33,
      "rank": 4,
      "market_cap_usd": 120446453172.09,
      "volume_24h": 704317640.6305264
    },
    {
      "symbol": "XRP",
      "name": "XRP",
      "price_usd": 1.93,
      "percent_change_24h": -0.37,
      "percent_change_1h": 0.5,
      "percent_change_7d": -2.94,
      "rank": 5,
      "market_cap_usd": 115280295324.23,
      "volume_24h": 1671523620.3665328
    },
    {
      "symbol": "USDC",
      "name": "USD Coin",
      "price_usd": 1,
      "percent_change_24h": 0,
      "percent_change_1h": 0,
      "percent_change_7d": 0.03,
      "rank": 6,
      "market_cap_usd": 73992551429.1,
      "volume_24h": 3876042804.5482316
    },
    {
      "symbol": "SOL",
      "name": "Solana",
      "price_usd": 126.69,
      "percent_change_24h": 0.59,
      "percent_change_1h": 0.43,
      "percent_change_7d": -2.48,
      "rank": 7,
      "market_cap_usd": 68813533636.34,
      "volume_24h": 2240986515.192963
    },
    {
      "symbol": "TRX",
      "name": "TRON",
      "price_usd": 0.286521,
      "percent_change_24h": 0.55,
      "percent_change_1h": -0.44,
      "percent_change_7d": 3.57,
      "rank": 8,
      "market_cap_usd": 27123808751.59,
      "volume_24h": 510667614.0265988
    },
    {
      "symbol": "DOGE",
      "name": "Dogecoin",
      "price_usd": 0.132327,
      "percent_change_24h": 0.19,
      "percent_change_1h": -0.11,
      "percent_change_7d": -1.19,
      "rank": 10,
      "market_cap_usd": 22215393273.85,
      "volume_24h": 775399117.3053545
    },
    {
      "symbol": "ADA",
      "name": "Cardano",
      "price_usd": 0.369135,
      "percent_change_24h": -0.38,
      "percent_change_1h": -0.23,
      "percent_change_7d": -6.57,
      "rank": 12,
      "market_cap_usd": 13215200399.03,
      "volume_24h": 398872996.98164463
    },
    {
      "symbol": "BCH",
      "name": "Bitcoin Cash",
      "price_usd": 583.4,
      "percent_change_24h": -0.57,
      "percent_change_1h": 0.49,
      "percent_change_7d": 4.64,
      "rank": 13,
      "market_cap_usd": 11648404760.8,
      "volume_24h": 295103587.0600667
    },
    {
      "symbol": "XMR",
      "name": "Monero",
      "price_usd": 467.16,
      "percent_change_24h": 0.12,
      "percent_change_1h": -1.26,
      "percent_change_7d": 14.03,
      "rank": 17,
      "market_cap_usd": 8617614039.35,
      "volume_24h": 200205683.61697826
    },
    {
      "symbol": "LINK",
      "name": "ChainLink",
      "price_usd": 12.68,
      "percent_change_24h": 0.52,
      "percent_change_1h": 0.2,
      "percent_change_7d": -4.52,
      "rank": 18,
      "market_cap_usd": 8601395582.54,
      "volume_24h": 355240187.13474596
    },
    {
      "symbol": "HYPE",
      "name": "Hyperliquid",
      "price_usd": 25.19,
      "percent_change_24h": 3.8,
      "percent_change_1h": -0.53,
      "percent_change_7d": -13.07,
      "rank": 19,
      "market_cap_usd": 8410246268.79,
      "volume_24h": 115344481.74453472
    },
    {
      "symbol": "ZEC",
      "name": "Zcash",
      "price_usd": 445.09,
      "percent_change_24h": 1.04,
      "percent_change_1h": -0.05,
      "percent_change_7d": 10.74,
      "rank": 21,
      "market_cap_usd": 7222210967.62,
      "volume_24h": 613943159.2409532
    },
    {
      "symbol": "LTC",
      "name": "Litecoin",
      "price_usd": 77.93,
      "percent_change_24h": 0.53,
      "percent_change_1h": -0.15,
      "percent_change_7d": -0.6,
      "rank": 24,
      "market_cap_usd": 5947843115.63,
      "volume_24h": 337106809.6515101
    },
    {
      "symbol": "AVAX",
      "name": "Avalanche",
      "price_usd": 12.27,
      "percent_change_24h": 0.39,
      "percent_change_1h": 0.37,
      "percent_change_7d": -4.6,
      "rank": 27,
      "market_cap_usd": 5182925560.1,
      "volume_24h": 182384355.17352602
    },
    {
      "symbol": "SHIB",
      "name": "Shiba Inu",
      "price_usd": 0.000007,
      "percent_change_24h": -1.7,
      "percent_change_1h": -0.26,
      "percent_change_7d": -9.89,
      "rank": 29,
      "market_cap_usd": 4283763298.32,
      "volume_24h": 19591689.63874265
    },
    {
      "symbol": "ETC",
      "name": "Ethereum Classic",
      "price_usd": 12.34,
      "percent_change_24h": -0.21,
      "percent_change_1h": -0.1,
      "percent_change_7d": -3.04,
      "rank": 41,
      "market_cap_usd": 1895234817.73,
      "volume_24h": 85111108.19936553
    },
    {
      "symbol": "PI",
      "name": "Pi",
      "price_usd": 0.206484,
      "percent_change_24h": -0.89,
      "percent_change_1h": 0.25,
      "percent_change_7d": 2,
      "rank": 42,
      "market_cap_usd": 1692449548.74,
      "volume_24h": 6714442.068226269
    },
    {
      "symbol": "PEPE",
      "name": "Pepe",
      "price_usd": 0.000004,
      "percent_change_24h": -1.96,
      "percent_change_1h": -0.09,
      "percent_change_7d": -3.62,
      "rank": 43,
      "market_cap_usd": 1684756369.98,
      "volume_24h": 5713096.740332841
    },
    {
      "symbol": "XAUT",
      "name": "Tether Gold",
      "price_usd": 4414.26,
      "percent_change_24h": 1.53,
      "percent_change_1h": 0,
      "percent_change_7d": 2.46,
      "rank": 46,
      "market_cap_usd": 1657874128.61,
      "volume_24h": 117532867.31707986
    },
    {
      "symbol": "KAS",
      "name": "Kaspa",
      "price_usd": 0.048017,
      "percent_change_24h": 6.67,
      "percent_change_1h": 0.99,
      "percent_change_7d": 7.8,
      "rank": 54,
      "market_cap_usd": 1283225628.22,
      "volume_24h": 25936655.720733773
    },
    {
      "symbol": "DASH",
      "name": "Dash",
      "price_usd": 38.2,
      "percent_change_24h": -3.16,
      "percent_change_1h": -0.88,
      "percent_change_7d": -7.17,
      "rank": 94,
      "market_cap_usd": 478096993.77,
      "volume_24h": 72706911.44630438
    },
    {
      "symbol": "RVN",
      "name": "Ravencoin",
      "price_usd": 0.007024,
      "percent_change_24h": 0.25,
      "percent_change_1h": 0.17,
      "percent_change_7d": -6.27,
      "rank": 230,
      "market_cap_usd": 109648593.34,
      "volume_24h": 5747665.199332031
    },
    {
      "symbol": "VTC",
      "name": "Vertcoin",
      "price_usd": 0.070306,
      "percent_change_24h": -3.28,
      "percent_change_1h": 0.47,
      "percent_change_7d": -2.5,
      "rank": 1017,
      "market_cap_usd": 5168838.81,
      "volume_24h": 13437.271411461381
    },
    {
      "symbol": "BELLS",
      "name": "Bellscoin",
      "price_usd": 0.084209,
      "percent_change_24h": -4.51,
      "percent_change_1h": -0.92,
      "percent_change_7d": 8.01,
      "rank": 1019,
      "market_cap_usd": 5140885.39,
      "volume_24h": 44141.38298034264
    }
  ]
}