{
  "last_updated": "2025-12-16T17:39:16.952Z",
  "source": "coinlore",
  "version": "1.0.0",
  "coins": [
    {
      "symbol": "BTC",
      "name": "Bitcoin",
      "price_usd": 87387.88,
      "percent_change_24h": 1.88,
      "percent_change_1h": -0.33,
      "percent_change_7d": -3.04,
      "rank": 1,
      "market_cap_usd": 1744417090937.3,
      "volume_24h": 40294797295.348175
    },
    {
      "symbol": "ETH",
      "name": "Ethereum",
      "price_usd": 2935.91,
      "percent_change_24h": -0.71,
      "percent_change_1h": -0.14,
      "percent_change_7d": -5.66,
      "rank": 2,
      "market_cap_usd": 354375637317.59,
      "volume_24h": 19604746036.618015
    },
    {
      "symbol": "USDT",
      "name": "Tether",
      "price_usd": 1,
      "percent_change_24h": -0.01,
      "percent_change_1h": -0.01,
      "percent_change_7d": -0.05,
      "rank": 3,
      "market_cap_usd": 171958867855.33,
      "volume_24h": 69092472569.08003
    },
    {
      "symbol": "BNB",
      "name": "Binance Coin",
      "price_usd": 869.8,
      "percent_change_24h": 2.85,
      "percent_change_1h": -0.31,
      "percent_change_7d": -2.44,
      "rank": 4,
      "market_cap_usd": 121063679740.3,
      "volume_24h": 1240259931.6174312
    },
    {
      "symbol": "XRP",
      "name": "XRP",
      "price_usd": 1.93,
      "percent_change_24h": 1.47,
      "percent_change_1h": 0.06,
      "percent_change_7d": -6.38,
      "rank": 5,
      "market_cap_usd": 115137513559.94,
      "volume_24h": 2839472808.235492
    },
    {
      "symbol": "USDC",
      "name": "USD Coin",
      "price_usd": 0.999819,
      "percent_change_24h": -0.01,
      "percent_change_1h": -0.01,
      "percent_change_7d": 0.01,
      "rank": 6,
      "market_cap_usd": 73965953822.22,
      "volume_24h": 6075050039.5078535
    },
    {
      "symbol": "SOL",
      "name": "Solana",
      "price_usd": 127.7,
      "percent_change_24h": 1.9,
      "percent_change_1h": -0.42,
      "percent_change_7d": -3.92,
      "rank": 7,
      "market_cap_usd": 69361264840.07,
      "volume_24h": 3614925970.8812695
    },
    {
      "symbol": "TRX",
      "name": "TRON",
      "price_usd": 0.28072,
      "percent_change_24h": 0.43,
      "percent_change_1h": -0.16,
      "percent_change_7d": -0.11,
      "rank": 8,
      "market_cap_usd": 26574686542.53,
      "volume_24h": 569824421.1479155
    },
    {
      "symbol": "DOGE",
      "name": "Dogecoin",
      "price_usd": 0.131548,
      "percent_change_24h": 2.16,
      "percent_change_1h": -0.16,
      "percent_change_7d": -6.41,
      "rank": 10,
      "market_cap_usd": 22084632820.05,
      "volume_24h": 1056666397.1948209
    },
    {
      "symbol": "ADA",
      "name": "Cardano",
      "price_usd": 0.387245,
      "percent_change_24h": 1.69,
      "percent_change_1h": -0.06,
      "percent_change_7d": -9.59,
      "rank": 12,
      "market_cap_usd": 13863546611.74,
      "volume_24h": 481209336.76693743
    },
    {
      "symbol": "BCH",
      "name": "Bitcoin Cash",
      "price_usd": 547.55,
      "percent_change_24h": 3.89,
      "percent_change_1h": 0.19,
      "percent_change_7d": -4.38,
      "rank": 14,
      "market_cap_usd": 10932529501.87,
      "volume_24h": 309055665.1601471
    },
    {
      "symbol": "HYPE",
      "name": "Hyperliquid",
      "price_usd": 26.52,
      "percent_change_24h": -3.27,
      "percent_change_1h": -2.04,
      "percent_change_7d": -5.62,
      "rank": 17,
      "market_cap_usd": 8855400155.47,
      "volume_24h": 205401687.03291118
    },
    {
      "symbol": "LINK",
      "name": "ChainLink",
      "price_usd": 12.93,
      "percent_change_24h": 2.17,
      "percent_change_1h": 0.07,
      "percent_change_7d": -5.75,
      "rank": 18,
      "market_cap_usd": 8766757339.29,
      "volume_24h": 528562704.5309586
    },
    {
      "symbol": "XMR",
      "name": "Monero",
      "price_usd": 428.87,
      "percent_change_24h": 4.61,
      "percent_change_1h": 0.65,
      "percent_change_7d": 14.75,
      "rank": 19,
      "market_cap_usd": 7911328513.14,
      "volume_24h": 209185787.99452838
    },
    {
      "symbol": "ZEC",
      "name": "Zcash",
      "price_usd": 406.36,
      "percent_change_24h": -1.88,
      "percent_change_1h": -0.51,
      "percent_change_7d": 1.63,
      "rank": 21,
      "market_cap_usd": 6593804317.23,
      "volume_24h": 953453023.7041881
    },
    {
      "symbol": "LTC",
      "name": "Litecoin",
      "price_usd": 79.09,
      "percent_change_24h": 3.09,
      "percent_change_1h": 0.1,
      "percent_change_7d": -4.89,
      "rank": 23,
      "market_cap_usd": 6036409197.93,
      "volume_24h": 521603671.59953356
    },
    {
      "symbol": "AVAX",
      "name": "Avalanche",
      "price_usd": 12.27,
      "percent_change_24h": -0.61,
      "percent_change_1h": -0.24,
      "percent_change_7d": -10.28,
      "rank": 26,
      "market_cap_usd": 5179280268.7,
      "volume_24h": 304292064.3381943
    },
    {
      "symbol": "SHIB",
      "name": "Shiba Inu",
      "price_usd": 0.000008,
      "percent_change_24h": 1.17,
      "percent_change_1h": -0.19,
      "percent_change_7d": -6.95,
      "rank": 28,
      "market_cap_usd": 4648588543.24,
      "volume_24h": 20065101.99689378
    },
    {
      "symbol": "ETC",
      "name": "Ethereum Classic",
      "price_usd": 12.65,
      "percent_change_24h": 3.88,
      "percent_change_1h": 0.63,
      "percent_change_7d": -5.11,
      "rank": 41,
      "market_cap_usd": 1943190397.59,
      "volume_24h": 147158611.67420113
    },
    {
      "symbol": "PEPE",
      "name": "Pepe",
      "price_usd": 0.000004,
      "percent_change_24h": 2.03,
      "percent_change_1h": 0.06,
      "percent_change_7d": -11.35,
      "rank": 42,
      "market_cap_usd": 1718970622.44,
      "volume_24h": 6099088.050310848
    },
    {
      "symbol": "XAUT",
      "name": "Tether Gold",
      "price_usd": 4307.16,
      "percent_change_24h": 0.03,
      "percent_change_1h": 0.1,
      "percent_change_7d": 2.94,
      "rank": 46,
      "market_cap_usd": 1617649743.17,
      "volume_24h": 152233375.51008797
    },
    {
      "symbol": "PI",
      "name": "Pi",
      "price_usd": 0.19681,
      "percent_change_24h": -0.49,
      "percent_change_1h": -0.34,
      "percent_change_7d": -10.39,
      "rank": 47,
      "market_cap_usd": 1613155817.98,
      "volume_24h": 13478952.813711371
    },
    {
      "symbol": "KAS",
      "name": "Kaspa",
      "price_usd": 0.044647,
      "percent_change_24h": 5.79,
      "percent_change_1h": 2.47,
      "percent_change_7d": -12.54,
      "rank": 55,
      "market_cap_usd": 1193155336.8,
      "volume_24h": 21135126.846919697
    },
    {
      "symbol": "DASH",
      "name": "Dash",
      "price_usd": 41.69,
      "percent_change_24h": 3.46,
      "percent_change_1h": -0.81,
      "percent_change_7d": -12.48,
      "rank": 90,
      "market_cap_usd": 521829747.25,
      "volume_24h": 114907322.34440945
    },
    {
      "symbol": "RVN",
      "name": "Ravencoin",
      "price_usd": 0.007366,
      "percent_change_24h": 2.03,
      "percent_change_1h": 0.03,
      "percent_change_7d": -7.15,
      "rank": 227,
      "market_cap_usd": 114992116.85,
      "volume_24h": 5958169.896954768
    },
    {
      "symbol": "VTC",
      "name": "Vertcoin",
      "price_usd": 0.070629,
      "percent_change_24h": -2.65,
      "percent_change_1h": 0.37,
      "percent_change_7d": 5.41,
      "rank": 1031,
      "market_cap_usd": 5192513.52,
      "volume_24h": 15333.63062408142
    },
    {
      "symbol": "BELLS",
      "name": "Bellscoin",
      "price_usd": 0.080404,
      "percent_change_24h": 1,
      "percent_change_1h": 0,
      "percent_change_7d": 6.13,
      "rank": 1053,
      "market_cap_usd": 4908584.4,
      "volume_24h": 29058.173364256265
    }
  ]
}